gg_scrape/__init__.py
gg_scrape/__main__.py
gg_scrape/argsparse.py
gg_scrape/champion_gg_scraper.py
gg_scrape/mobalytics_scraper.py
gg_scrape/print_tree.py
gg_scrape-0.1.8.dist-info/entry_points.txt
gg_scrape-0.1.8.dist-info/WHEEL
gg_scrape-0.1.8.dist-info/METADATA
gg_scrape-0.1.8.dist-info/RECORD
