Metadata-Version: 2.1
Name: gg-scrape
Version: 0.1.8
Summary: A little Python CLI app that provides a summary of League champion build information. 
Home-page: https://github.com/teauxfu/gg-scrape
Author: Alex W
Author-email: alex@southsun.tech
Requires-Python: >=3.9,<4.0
Classifier: Programming Language :: Python :: 3
Classifier: Programming Language :: Python :: 3.9
Requires-Dist: anytree (>=2.8.0,<3.0.0)
Requires-Dist: beautifulsoup4 (>=4.9.3,<5.0.0)
Requires-Dist: requests (>=2.25.1,<3.0.0)
Requires-Dist: typer (>=0.3.2,<0.4.0)
Project-URL: Repository, https://github.com/teauxfu/gg-scrape
